reko/__init__.py
reko/__main__.py
reko/__version__.py
reko/api.py
reko/cli.py
reko/adapters/__init__.py
reko/adapters/storage.py
reko/adapters/youtube.py
reko/adapters/dspy/__init__.py
reko/adapters/dspy/config.py
reko/adapters/dspy/modules.py
reko/adapters/dspy/signatures.py
reko/core/__init__.py
reko/core/chunking.py
reko/core/errors.py
reko/core/markdown.py
reko/core/models.py
reko/core/prompt.py
reko/core/services.py
reko/core/summarizer.py
reko/core/text_utils.py
reko/core/transcript.py
reko/core/translation.py
reko/web/static/app.js
reko/web/static/style.css
reko/web/templates/index.html
reko_yt-0.1.1.dist-info/licenses/LICENSE
reko_yt-0.1.1.dist-info/METADATA
reko_yt-0.1.1.dist-info/WHEEL
reko_yt-0.1.1.dist-info/entry_points.txt
reko_yt-0.1.1.dist-info/top_level.txt
reko_yt-0.1.1.dist-info/RECORD
