Metadata-Version: 2.4
Name: reko-yt
Version: 0.1.1
Summary: A modern, local-first CLI tool to extract transcripts from YouTube and transform them into concise summaries and key points.
Author-email: Riccardo Ruspoli <riccardoruspoli@gmail.com>
License-Expression: MIT
Project-URL: Homepage, https://github.com/riccardoruspoli/reko
Project-URL: Repository, https://github.com/riccardoruspoli/reko
Project-URL: Issues, https://github.com/riccardoruspoli/reko/issues
Keywords: youtube,summarization,llm,cli,ollama,transcript
Classifier: Development Status :: 4 - Beta
Classifier: Environment :: Console
Classifier: Intended Audience :: Developers
Classifier: Programming Language :: Python :: 3
Classifier: Programming Language :: Python :: 3 :: Only
Classifier: Programming Language :: Python :: 3.10
Classifier: Programming Language :: Python :: 3.11
Classifier: Programming Language :: Python :: 3.12
Classifier: Programming Language :: Python :: 3.13
Classifier: Topic :: Multimedia :: Video
Classifier: Topic :: Text Processing :: Linguistic
Requires-Python: <3.14,>=3.10
License-File: LICENSE
Requires-Dist: dspy>=3.0.4
Requires-Dist: fastapi>=0.128.0
Requires-Dist: iso639-lang>=2.6.3
Requires-Dist: jinja2>=3.1.6
Requires-Dist: markdown>=3.10
Requires-Dist: ollama>=0.6.1
Requires-Dist: pytubefix>=10.3.6
Requires-Dist: tqdm>=4.67.1
Requires-Dist: uvicorn>=0.40.0
Requires-Dist: youtube-transcript-api>=1.2.3
Provides-Extra: dev
Requires-Dist: ruff; extra == "dev"
Requires-Dist: tox>=4; extra == "dev"
Requires-Dist: build; extra == "dev"
Requires-Dist: twine; extra == "dev"
Dynamic: license-file
